{
  "conceptSetId": 141,
  "resolvedConcepts": [
    {
      "conceptId": 40747709,
      "conceptName": "Dopamine 0.6 MG/ML Injectable Solution",
      "vocabularyId": "RxNorm Extension",
      "domainId": "Drug",
      "conceptClassId": "Clinical Drug",
      "conceptCode": "OMOP4709595",
      "standardConcept": "S"
    },
    {
      "conceptId": 42966510,
      "conceptName": "Dopamine 0.8 MG/ML / Glucose 50 MG/ML Injectable Solution",
      "vocabularyId": "RxNorm Extension",
      "domainId": "Drug",
      "conceptClassId": "Clinical Drug",
      "conceptCode": "OMOP4692969",
      "standardConcept": "S"
    },
    {
      "conceptId": 44123506,
      "conceptName": "Dopamine 0.8 MG/ML / Glucose 50 MG/ML Injection",
      "vocabularyId": "RxNorm Extension",
      "domainId": "Drug",
      "conceptClassId": "Clinical Drug",
      "conceptCode": "OMOP1118137",
      "standardConcept": "S"
    },
    {
      "conceptId": 35159013,
      "conceptName": "Dopamine 1 MG/ML Prefilled Syringe",
      "vocabularyId": "RxNorm Extension",
      "domainId": "Drug",
      "conceptClassId": "Clinical Drug",
      "conceptCode": "OMOP4816000",
      "standardConcept": "S"
    },
    {
      "conceptId": 40747701,
      "conceptName": "Dopamine 1.2 MG/ML Injectable Solution",
      "vocabularyId": "RxNorm Extension",
      "domainId": "Drug",
      "conceptClassId": "Clinical Drug",
      "conceptCode": "OMOP4709603",
      "standardConcept": "S"
    },
    {
      "conceptId": 42966516,
      "conceptName": "Dopamine 1.6 MG/ML / Glucose 50 MG/ML Injectable Solution",
      "vocabularyId": "RxNorm Extension",
      "domainId": "Drug",
      "conceptClassId": "Clinical Drug",
      "conceptCode": "OMOP4692975",
      "standardConcept": "S"
    },
    {
      "conceptId": 44058822,
      "conceptName": "Dopamine 1.6 MG/ML / Glucose 50 MG/ML Injection",
      "vocabularyId": "RxNorm Extension",
      "domainId": "Drug",
      "conceptClassId": "Clinical Drug",
      "conceptCode": "OMOP1053453",
      "standardConcept": "S"
    },
    {
      "conceptId": 36404300,
      "conceptName": "Dopamine 1.6 MG/ML Injectable Solution",
      "vocabularyId": "RxNorm Extension",
      "domainId": "Drug",
      "conceptClassId": "Clinical Drug",
      "conceptCode": "OMOP3096342",
      "standardConcept": "S"
    },
    {
      "conceptId": 42482746,
      "conceptName": "Dopamine 1.6 MG/ML Prefilled Syringe",
      "vocabularyId": "RxNorm Extension",
      "domainId": "Drug",
      "conceptClassId": "Clinical Drug",
      "conceptCode": "OMOP419726",
      "standardConcept": "S"
    },
    {
      "conceptId": 36881070,
      "conceptName": "Dopamine 10 MG/ML Injection",
      "vocabularyId": "RxNorm Extension",
      "domainId": "Drug",
      "conceptClassId": "Clinical Drug",
      "conceptCode": "OMOP987927",
      "standardConcept": "S"
    },
    {
      "conceptId": 36885858,
      "conceptName": "Dopamine 10 MG/ML Prefilled Syringe",
      "vocabularyId": "RxNorm Extension",
      "domainId": "Drug",
      "conceptClassId": "Clinical Drug",
      "conceptCode": "OMOP991122",
      "standardConcept": "S"
    },
    {
      "conceptId": 36405824,
      "conceptName": "Dopamine 160 MG/ML Injectable Solution",
      "vocabularyId": "RxNorm Extension",
      "domainId": "Drug",
      "conceptClassId": "Clinical Drug",
      "conceptCode": "OMOP3097866",
      "standardConcept": "S"
    },
    {
      "conceptId": 42966519,
      "conceptName": "Dopamine 2 MG/ML / Glucose 50 MG/ML Injectable Solution",
      "vocabularyId": "RxNorm Extension",
      "domainId": "Drug",
      "conceptClassId": "Clinical Drug",
      "conceptCode": "OMOP4692978",
      "standardConcept": "S"
    },
    {
      "conceptId": 40747705,
      "conceptName": "Dopamine 2.4 MG/ML Injectable Solution",
      "vocabularyId": "RxNorm Extension",
      "domainId": "Drug",
      "conceptClassId": "Clinical Drug",
      "conceptCode": "OMOP4709599",
      "standardConcept": "S"
    },
    {
      "conceptId": 36882038,
      "conceptName": "Dopamine 20 MG/ML Injection",
      "vocabularyId": "RxNorm Extension",
      "domainId": "Drug",
      "conceptClassId": "Clinical Drug",
      "conceptCode": "OMOP988577",
      "standardConcept": "S"
    },
    {
      "conceptId": 35146356,
      "conceptName": "Dopamine 3 MG/ML Injectable Solution",
      "vocabularyId": "RxNorm Extension",
      "domainId": "Drug",
      "conceptClassId": "Clinical Drug",
      "conceptCode": "OMOP4803436",
      "standardConcept": "S"
    },
    {
      "conceptId": 35133820,
      "conceptName": "Dopamine 3 MG/ML Prefilled Syringe",
      "vocabularyId": "RxNorm Extension",
      "domainId": "Drug",
      "conceptClassId": "Clinical Drug",
      "conceptCode": "OMOP4791026",
      "standardConcept": "S"
    },
    {
      "conceptId": 42966513,
      "conceptName": "Dopamine 3.2 MG/ML / Glucose 50 MG/ML Injectable Solution",
      "vocabularyId": "RxNorm Extension",
      "domainId": "Drug",
      "conceptClassId": "Clinical Drug",
      "conceptCode": "OMOP4692972",
      "standardConcept": "S"
    },
    {
      "conceptId": 44071651,
      "conceptName": "Dopamine 3.2 MG/ML / Glucose 50 MG/ML Injection",
      "vocabularyId": "RxNorm Extension",
      "domainId": "Drug",
      "conceptClassId": "Clinical Drug",
      "conceptCode": "OMOP1066282",
      "standardConcept": "S"
    },
    {
      "conceptId": 41148968,
      "conceptName": "Dopamine 3.2 MG/ML Injectable Solution",
      "vocabularyId": "RxNorm Extension",
      "domainId": "Drug",
      "conceptClassId": "Clinical Drug",
      "conceptCode": "OMOP2346930",
      "standardConcept": "S"
    },
    {
      "conceptId": 42482197,
      "conceptName": "Dopamine 3.2 MG/ML Prefilled Syringe",
      "vocabularyId": "RxNorm Extension",
      "domainId": "Drug",
      "conceptClassId": "Clinical Drug",
      "conceptCode": "OMOP419728",
      "standardConcept": "S"
    },
    {
      "conceptId": 36404301,
      "conceptName": "Dopamine 4 MG/ML Injectable Solution",
      "vocabularyId": "RxNorm Extension",
      "domainId": "Drug",
      "conceptClassId": "Clinical Drug",
      "conceptCode": "OMOP3096343",
      "standardConcept": "S"
    },
    {
      "conceptId": 21036806,
      "conceptName": "Dopamine 4 MG/ML Injection",
      "vocabularyId": "RxNorm Extension",
      "domainId": "Drug",
      "conceptClassId": "Clinical Drug",
      "conceptCode": "OMOP269850",
      "standardConcept": "S"
    },
    {
      "conceptId": 44045773,
      "conceptName": "Dopamine 40 MG/ML Injectable Solution",
      "vocabularyId": "RxNorm Extension",
      "domainId": "Drug",
      "conceptClassId": "Clinical Drug",
      "conceptCode": "OMOP1040404",
      "standardConcept": "S"
    },
    {
      "conceptId": 36890769,
      "conceptName": "Dopamine 5 MG/ML Injection",
      "vocabularyId": "RxNorm Extension",
      "domainId": "Drug",
      "conceptClassId": "Clinical Drug",
      "conceptCode": "OMOP993704",
      "standardConcept": "S"
    },
    {
      "conceptId": 36892742,
      "conceptName": "Dopamine 5 MG/ML Prefilled Syringe",
      "vocabularyId": "RxNorm Extension",
      "domainId": "Drug",
      "conceptClassId": "Clinical Drug",
      "conceptCode": "OMOP1003851",
      "standardConcept": "S"
    },
    {
      "conceptId": 35158764,
      "conceptName": "Dopamine 6 MG/ML Prefilled Syringe",
      "vocabularyId": "RxNorm Extension",
      "domainId": "Drug",
      "conceptClassId": "Clinical Drug",
      "conceptCode": "OMOP4815754",
      "standardConcept": "S"
    },
    {
      "conceptId": 42966539,
      "conceptName": "Dopamine 80 MG/ML Injectable Solution",
      "vocabularyId": "RxNorm Extension",
      "domainId": "Drug",
      "conceptClassId": "Clinical Drug",
      "conceptCode": "OMOP4692998",
      "standardConcept": "S"
    },
    {
      "conceptId": 2062427,
      "conceptName": "dopamine 1 MG/ML / glucose 50 MG/ML Injectable Solution",
      "vocabularyId": "RxNorm Extension",
      "domainId": "Drug",
      "conceptClassId": "Clinical Drug",
      "conceptCode": "OMOP4963679",
      "standardConcept": "S"
    },
    {
      "conceptId": 35867374,
      "conceptName": "dopamine 10 MG Injectable Solution",
      "vocabularyId": "RxNorm Extension",
      "domainId": "Drug",
      "conceptClassId": "Clinical Drug",
      "conceptCode": "OMOP5024296",
      "standardConcept": "S"
    },
    {
      "conceptId": 2062431,
      "conceptName": "dopamine 160 MG/ML Prefilled Syringe",
      "vocabularyId": "RxNorm Extension",
      "domainId": "Drug",
      "conceptClassId": "Clinical Drug",
      "conceptCode": "OMOP4963683",
      "standardConcept": "S"
    },
    {
      "conceptId": 35867371,
      "conceptName": "dopamine 20 MG Injectable Solution",
      "vocabularyId": "RxNorm Extension",
      "domainId": "Drug",
      "conceptClassId": "Clinical Drug",
      "conceptCode": "OMOP5024293",
      "standardConcept": "S"
    },
    {
      "conceptId": 2062424,
      "conceptName": "dopamine 4 MG/ML / glucose 50 MG/ML Injectable Solution",
      "vocabularyId": "RxNorm Extension",
      "domainId": "Drug",
      "conceptClassId": "Clinical Drug",
      "conceptCode": "OMOP4963676",
      "standardConcept": "S"
    },
    {
      "conceptId": 35867377,
      "conceptName": "dopamine 5 MG Injectable Solution",
      "vocabularyId": "RxNorm Extension",
      "domainId": "Drug",
      "conceptClassId": "Clinical Drug",
      "conceptCode": "OMOP5024299",
      "standardConcept": "S"
    },
    {
      "conceptId": 2062432,
      "conceptName": "dopamine 80 MG/ML Prefilled Syringe",
      "vocabularyId": "RxNorm Extension",
      "domainId": "Drug",
      "conceptClassId": "Clinical Drug",
      "conceptCode": "OMOP4963684",
      "standardConcept": "S"
    },
    {
      "conceptId": 42799669,
      "conceptName": "dopamine hydrochloride 0.4 MG/ML Injectable Solution",
      "vocabularyId": "RxNorm",
      "domainId": "Drug",
      "conceptClassId": "Clinical Drug",
      "conceptCode": "1293170",
      "standardConcept": "S"
    },
    {
      "conceptId": 35606562,
      "conceptName": "dopamine hydrochloride 0.8 MG/ML Injection",
      "vocabularyId": "RxNorm",
      "domainId": "Drug",
      "conceptClassId": "Clinical Drug",
      "conceptCode": "1743870",
      "standardConcept": "S"
    },
    {
      "conceptId": 42799673,
      "conceptName": "dopamine hydrochloride 1 MG/ML Injectable Solution",
      "vocabularyId": "RxNorm",
      "domainId": "Drug",
      "conceptClassId": "Clinical Drug",
      "conceptCode": "1292742",
      "standardConcept": "S"
    },
    {
      "conceptId": 35606565,
      "conceptName": "dopamine hydrochloride 1.6 MG/ML Injection",
      "vocabularyId": "RxNorm",
      "domainId": "Drug",
      "conceptClassId": "Clinical Drug",
      "conceptCode": "1743878",
      "standardConcept": "S"
    },
    {
      "conceptId": 42799677,
      "conceptName": "dopamine hydrochloride 10 MG/ML Injectable Solution",
      "vocabularyId": "RxNorm",
      "domainId": "Drug",
      "conceptClassId": "Clinical Drug",
      "conceptCode": "1292764",
      "standardConcept": "S"
    },
    {
      "conceptId": 42799679,
      "conceptName": "dopamine hydrochloride 12 MG/ML Injectable Solution",
      "vocabularyId": "RxNorm",
      "domainId": "Drug",
      "conceptClassId": "Clinical Drug",
      "conceptCode": "1292767",
      "standardConcept": "S"
    },
    {
      "conceptId": 35606560,
      "conceptName": "dopamine hydrochloride 160 MG/ML Injection",
      "vocabularyId": "RxNorm",
      "domainId": "Drug",
      "conceptClassId": "Clinical Drug",
      "conceptCode": "1743866",
      "standardConcept": "S"
    },
    {
      "conceptId": 42799681,
      "conceptName": "dopamine hydrochloride 20 MG/ML Injectable Solution",
      "vocabularyId": "RxNorm",
      "domainId": "Drug",
      "conceptClassId": "Clinical Drug",
      "conceptCode": "1292883",
      "standardConcept": "S"
    },
    {
      "conceptId": 42799683,
      "conceptName": "dopamine hydrochloride 25 MG/ML Injectable Solution",
      "vocabularyId": "RxNorm",
      "domainId": "Drug",
      "conceptClassId": "Clinical Drug",
      "conceptCode": "1292885",
      "standardConcept": "S"
    },
    {
      "conceptId": 35606559,
      "conceptName": "dopamine hydrochloride 3.2 MG/ML Injection",
      "vocabularyId": "RxNorm",
      "domainId": "Drug",
      "conceptClassId": "Clinical Drug",
      "conceptCode": "1743864",
      "standardConcept": "S"
    },
    {
      "conceptId": 35606568,
      "conceptName": "dopamine hydrochloride 40 MG/ML Injection",
      "vocabularyId": "RxNorm",
      "domainId": "Drug",
      "conceptClassId": "Clinical Drug",
      "conceptCode": "1743939",
      "standardConcept": "S"
    },
    {
      "conceptId": 42902632,
      "conceptName": "dopamine hydrochloride 40 MG/ML Prefilled Syringe",
      "vocabularyId": "RxNorm",
      "domainId": "Drug",
      "conceptClassId": "Clinical Drug",
      "conceptCode": "1359745",
      "standardConcept": "S"
    },
    {
      "conceptId": 42799705,
      "conceptName": "dopamine hydrochloride 5 MG/ML Injectable Solution",
      "vocabularyId": "RxNorm",
      "domainId": "Drug",
      "conceptClassId": "Clinical Drug",
      "conceptCode": "1292889",
      "standardConcept": "S"
    },
    {
      "conceptId": 42799707,
      "conceptName": "dopamine hydrochloride 6.4 MG/ML Injectable Solution",
      "vocabularyId": "RxNorm",
      "domainId": "Drug",
      "conceptClassId": "Clinical Drug",
      "conceptCode": "1292899",
      "standardConcept": "S"
    },
    {
      "conceptId": 35606571,
      "conceptName": "dopamine hydrochloride 80 MG/ML Injection",
      "vocabularyId": "RxNorm",
      "domainId": "Drug",
      "conceptClassId": "Clinical Drug",
      "conceptCode": "1743951",
      "standardConcept": "S"
    }
  ]
}