{
  "id": 233,
  "name": "Enterobacter cloacae",
  "description": null,
  "version": "1.0.0",
  "createdBy": "Boris Delange",
  "createdDate": "2025-01-26",
  "modifiedBy": "Boris Delange",
  "modifiedDate": "2025-01-26",
  "createdByTool": "INDICATE Data Dictionary v0.2.0.9001",
  "expression": {
    "items": [
      {
        "concept": {
          "conceptId": 4030716,
          "conceptName": "Enterobacter cloacae",
          "standardConcept": "S",
          "standardConceptCaption": "Standard",
          "invalidReasonCaption": "Valid",
          "conceptCode": "14385002",
          "domainId": "Observation",
          "vocabularyId": "SNOMED",
          "conceptClassId": "Organism",
          "validStartDate": "2002-01-31",
          "validEndDate": "2099-12-31"
        },
        "isExcluded": false,
        "includeDescendants": false,
        "includeMapped": false
      },
      {
        "concept": {
          "conceptId": 4210735,
          "conceptName": "Enterobacter cloacae subspecies dissolvens",
          "standardConcept": "S",
          "standardConceptCaption": "Standard",
          "invalidReasonCaption": "Valid",
          "conceptCode": "56813009",
          "domainId": "Observation",
          "vocabularyId": "SNOMED",
          "conceptClassId": "Organism",
          "validStartDate": "2002-01-31",
          "validEndDate": "2099-12-31"
        },
        "isExcluded": false,
        "includeDescendants": false,
        "includeMapped": false
      },
      {
        "concept": {
          "conceptId": 37017689,
          "conceptName": "Carbapenem resistant Enterobacter cloacae",
          "standardConcept": "S",
          "standardConceptCaption": "Standard",
          "invalidReasonCaption": "Valid",
          "conceptCode": "714007005",
          "domainId": "Observation",
          "vocabularyId": "SNOMED",
          "conceptClassId": "Organism",
          "validStartDate": "2016-01-31",
          "validEndDate": "2099-12-31"
        },
        "isExcluded": false,
        "includeDescendants": false,
        "includeMapped": false
      },
      {
        "concept": {
          "conceptId": 37017942,
          "conceptName": "Multiple drug-resistant Enterobacter cloacae",
          "standardConcept": "S",
          "standardConceptCaption": "Standard",
          "invalidReasonCaption": "Valid",
          "conceptCode": "714317005",
          "domainId": "Observation",
          "vocabularyId": "SNOMED",
          "conceptClassId": "Organism",
          "validStartDate": "2016-01-31",
          "validEndDate": "2099-12-31"
        },
        "isExcluded": false,
        "includeDescendants": false,
        "includeMapped": false
      },
      {
        "concept": {
          "conceptId": 36716067,
          "conceptName": "Extended spectrum beta-lactamase producing Enterobacter cloacae",
          "standardConcept": "S",
          "standardConceptCaption": "Standard",
          "invalidReasonCaption": "Valid",
          "conceptCode": "721910001",
          "domainId": "Observation",
          "vocabularyId": "SNOMED",
          "conceptClassId": "Organism",
          "validStartDate": "2017-01-31",
          "validEndDate": "2099-12-31"
        },
        "isExcluded": false,
        "includeDescendants": false,
        "includeMapped": false
      },
      {
        "concept": {
          "conceptId": 36717518,
          "conceptName": "Enterobacter cloacae subsp. cloacae",
          "standardConcept": "S",
          "standardConceptCaption": "Standard",
          "invalidReasonCaption": "Valid",
          "conceptCode": "721950003",
          "domainId": "Observation",
          "vocabularyId": "SNOMED",
          "conceptClassId": "Organism",
          "validStartDate": "2017-01-31",
          "validEndDate": "2099-12-31"
        },
        "isExcluded": false,
        "includeDescendants": false,
        "includeMapped": false
      },
      {
        "concept": {
          "conceptId": 42537866,
          "conceptName": "Carbapenemase-producing Enterobacter cloacae",
          "standardConcept": "S",
          "standardConceptCaption": "Standard",
          "invalidReasonCaption": "Valid",
          "conceptCode": "737529000",
          "domainId": "Observation",
          "vocabularyId": "SNOMED",
          "conceptClassId": "Organism",
          "validStartDate": "2018-01-31",
          "validEndDate": "2099-12-31"
        },
        "isExcluded": false,
        "includeDescendants": false,
        "includeMapped": false
      }
    ]
  },
  "tags": [],
  "metadata": {
    "translations": {
      "en": {
        "name": "Enterobacter cloacae",
        "category": "Microbiology",
        "subcategory": "Microorganism"
      },
      "fr": {
        "name": "Enterobacter cloacae",
        "category": "Microbiologie",
        "subcategory": "Micro-organisme"
      }
    },
    "createdByDetails": {
      "firstName": "Boris",
      "lastName": "Delange",
      "affiliation": "Univ Rennes, CHU Rennes, INSERM, LTSI-UMR 1099, Rennes, France",
      "profession": "Medical Informatics and Intensive Care Physician",
      "orcid": "0009-0002-6055-6935"
    },
    "reviews": [],
    "versions": [],
    "distributionStats": null
  }
}
