{
  "id": 92,
  "name": "Levofloxacin",
  "description": null,
  "version": "1.0.0",
  "createdBy": "Boris Delange",
  "createdDate": "2025-01-26",
  "modifiedBy": "Boris Delange",
  "modifiedDate": "2025-01-26",
  "createdByTool": "INDICATE Data Dictionary v0.2.0.9001",
  "expression": {
    "items": [
      {
        "concept": {
          "conceptId": 46287441,
          "conceptName": "levofloxacin 5 MG/ML Injection",
          "standardConcept": "S",
          "standardConceptCaption": "Standard",
          "invalidReasonCaption": "Valid",
          "conceptCode": "1665505",
          "domainId": "Drug",
          "vocabularyId": "RxNorm",
          "conceptClassId": "Clinical Drug",
          "validStartDate": "2015-10-05",
          "validEndDate": "2099-12-31"
        },
        "isExcluded": false,
        "includeDescendants": false,
        "includeMapped": false
      },
      {
        "concept": {
          "conceptId": 46287452,
          "conceptName": "levofloxacin 25 MG/ML Injection",
          "standardConcept": "S",
          "standardConceptCaption": "Standard",
          "invalidReasonCaption": "Valid",
          "conceptCode": "1665518",
          "domainId": "Drug",
          "vocabularyId": "RxNorm",
          "conceptClassId": "Clinical Drug",
          "validStartDate": "2015-10-05",
          "validEndDate": "2099-12-31"
        },
        "isExcluded": false,
        "includeDescendants": false,
        "includeMapped": false
      },
      {
        "concept": {
          "conceptId": 1742254,
          "conceptName": "levofloxacin 250 MG Oral Tablet",
          "standardConcept": "S",
          "standardConceptCaption": "Standard",
          "invalidReasonCaption": "Valid",
          "conceptCode": "199884",
          "domainId": "Drug",
          "vocabularyId": "RxNorm",
          "conceptClassId": "Clinical Drug",
          "validStartDate": "1970-01-01",
          "validEndDate": "2099-12-31"
        },
        "isExcluded": false,
        "includeDescendants": false,
        "includeMapped": false
      },
      {
        "concept": {
          "conceptId": 1742255,
          "conceptName": "levofloxacin 500 MG Oral Tablet",
          "standardConcept": "S",
          "standardConceptCaption": "Standard",
          "invalidReasonCaption": "Valid",
          "conceptCode": "199885",
          "domainId": "Drug",
          "vocabularyId": "RxNorm",
          "conceptClassId": "Clinical Drug",
          "validStartDate": "1970-01-01",
          "validEndDate": "2099-12-31"
        },
        "isExcluded": false,
        "includeDescendants": false,
        "includeMapped": false
      },
      {
        "concept": {
          "conceptId": 1742284,
          "conceptName": "levofloxacin 750 MG Oral Tablet",
          "standardConcept": "S",
          "standardConceptCaption": "Standard",
          "invalidReasonCaption": "Valid",
          "conceptCode": "311296",
          "domainId": "Drug",
          "vocabularyId": "RxNorm",
          "conceptClassId": "Clinical Drug",
          "validStartDate": "1970-01-01",
          "validEndDate": "2099-12-31"
        },
        "isExcluded": false,
        "includeDescendants": false,
        "includeMapped": false
      },
      {
        "concept": {
          "conceptId": 19080152,
          "conceptName": "levofloxacin 5 MG/ML Ophthalmic Solution",
          "standardConcept": "S",
          "standardConceptCaption": "Standard",
          "invalidReasonCaption": "Valid",
          "conceptCode": "314080",
          "domainId": "Drug",
          "vocabularyId": "RxNorm",
          "conceptClassId": "Clinical Drug",
          "validStartDate": "1970-01-01",
          "validEndDate": "2099-12-31"
        },
        "isExcluded": false,
        "includeDescendants": false,
        "includeMapped": false
      },
      {
        "concept": {
          "conceptId": 43768057,
          "conceptName": "Levofloxacin 5 MG/ML Prefilled Applicator",
          "standardConcept": "S",
          "standardConceptCaption": "Standard",
          "invalidReasonCaption": "Valid",
          "conceptCode": "OMOP694343",
          "domainId": "Drug",
          "vocabularyId": "RxNorm Extension",
          "conceptClassId": "Clinical Drug",
          "validStartDate": "2017-08-24",
          "validEndDate": "2099-12-31"
        },
        "isExcluded": false,
        "includeDescendants": false,
        "includeMapped": false
      },
      {
        "concept": {
          "conceptId": 42479165,
          "conceptName": "Levofloxacin 5 MG/ML Injectable Solution",
          "standardConcept": "S",
          "standardConceptCaption": "Standard",
          "invalidReasonCaption": "Valid",
          "conceptCode": "OMOP420164",
          "domainId": "Drug",
          "vocabularyId": "RxNorm Extension",
          "conceptClassId": "Clinical Drug",
          "validStartDate": "2017-08-24",
          "validEndDate": "2099-12-31"
        },
        "isExcluded": false,
        "includeDescendants": false,
        "includeMapped": false
      },
      {
        "concept": {
          "conceptId": 36951903,
          "conceptName": "dexamethasone 1 MG/ML / levofloxacin 5 MG/ML Ophthalmic Solution",
          "standardConcept": "S",
          "standardConceptCaption": "Standard",
          "invalidReasonCaption": "Valid",
          "conceptCode": "OMOP5195330",
          "domainId": "Drug",
          "vocabularyId": "RxNorm Extension",
          "conceptClassId": "Clinical Drug",
          "validStartDate": "2023-05-22",
          "validEndDate": "2099-12-31"
        },
        "isExcluded": false,
        "includeDescendants": false,
        "includeMapped": false
      },
      {
        "concept": {
          "conceptId": 44110030,
          "conceptName": "Levofloxacin 100 MG/ML Inhalant Solution",
          "standardConcept": "S",
          "standardConceptCaption": "Standard",
          "invalidReasonCaption": "Valid",
          "conceptCode": "OMOP1104661",
          "domainId": "Drug",
          "vocabularyId": "RxNorm Extension",
          "conceptClassId": "Clinical Drug",
          "validStartDate": "2017-08-24",
          "validEndDate": "2099-12-31"
        },
        "isExcluded": false,
        "includeDescendants": false,
        "includeMapped": false
      },
      {
        "concept": {
          "conceptId": 35860708,
          "conceptName": "levofloxacin 500 MG Injectable Solution",
          "standardConcept": "S",
          "standardConceptCaption": "Standard",
          "invalidReasonCaption": "Valid",
          "conceptCode": "OMOP5017135",
          "domainId": "Drug",
          "vocabularyId": "RxNorm Extension",
          "conceptClassId": "Clinical Drug",
          "validStartDate": "2020-10-02",
          "validEndDate": "2099-12-31"
        },
        "isExcluded": false,
        "includeDescendants": false,
        "includeMapped": false
      },
      {
        "concept": {
          "conceptId": 35860721,
          "conceptName": "levofloxacin 250 MG Oral Capsule",
          "standardConcept": "S",
          "standardConceptCaption": "Standard",
          "invalidReasonCaption": "Valid",
          "conceptCode": "OMOP5017148",
          "domainId": "Drug",
          "vocabularyId": "RxNorm Extension",
          "conceptClassId": "Clinical Drug",
          "validStartDate": "2020-10-02",
          "validEndDate": "2099-12-31"
        },
        "isExcluded": false,
        "includeDescendants": false,
        "includeMapped": false
      },
      {
        "concept": {
          "conceptId": 35860722,
          "conceptName": "levofloxacin 250 MG Injectable Solution",
          "standardConcept": "S",
          "standardConceptCaption": "Standard",
          "invalidReasonCaption": "Valid",
          "conceptCode": "OMOP5017149",
          "domainId": "Drug",
          "vocabularyId": "RxNorm Extension",
          "conceptClassId": "Clinical Drug",
          "validStartDate": "2020-10-02",
          "validEndDate": "2099-12-31"
        },
        "isExcluded": false,
        "includeDescendants": false,
        "includeMapped": false
      },
      {
        "concept": {
          "conceptId": 35860738,
          "conceptName": "levofloxacin 100 MG Oral Capsule",
          "standardConcept": "S",
          "standardConceptCaption": "Standard",
          "invalidReasonCaption": "Valid",
          "conceptCode": "OMOP5017165",
          "domainId": "Drug",
          "vocabularyId": "RxNorm Extension",
          "conceptClassId": "Clinical Drug",
          "validStartDate": "2020-10-02",
          "validEndDate": "2099-12-31"
        },
        "isExcluded": false,
        "includeDescendants": false,
        "includeMapped": false
      },
      {
        "concept": {
          "conceptId": 35860749,
          "conceptName": "levofloxacin 100 MG Injectable Solution",
          "standardConcept": "S",
          "standardConceptCaption": "Standard",
          "invalidReasonCaption": "Valid",
          "conceptCode": "OMOP5017176",
          "domainId": "Drug",
          "vocabularyId": "RxNorm Extension",
          "conceptClassId": "Clinical Drug",
          "validStartDate": "2020-10-02",
          "validEndDate": "2099-12-31"
        },
        "isExcluded": false,
        "includeDescendants": false,
        "includeMapped": false
      },
      {
        "concept": {
          "conceptId": 35860337,
          "conceptName": "levofloxacin 100 MG/ML Injectable Solution",
          "standardConcept": "S",
          "standardConceptCaption": "Standard",
          "invalidReasonCaption": "Valid",
          "conceptCode": "OMOP5017237",
          "domainId": "Drug",
          "vocabularyId": "RxNorm Extension",
          "conceptClassId": "Clinical Drug",
          "validStartDate": "2020-10-02",
          "validEndDate": "2099-12-31"
        },
        "isExcluded": false,
        "includeDescendants": false,
        "includeMapped": false
      },
      {
        "concept": {
          "conceptId": 35861059,
          "conceptName": "levofloxacin 10 MG/ML Injectable Solution",
          "standardConcept": "S",
          "standardConceptCaption": "Standard",
          "invalidReasonCaption": "Valid",
          "conceptCode": "OMOP5017250",
          "domainId": "Drug",
          "vocabularyId": "RxNorm Extension",
          "conceptClassId": "Clinical Drug",
          "validStartDate": "2020-10-02",
          "validEndDate": "2099-12-31"
        },
        "isExcluded": false,
        "includeDescendants": false,
        "includeMapped": false
      },
      {
        "concept": {
          "conceptId": 35861061,
          "conceptName": "levofloxacin 5 MG/ML Otic Solution",
          "standardConcept": "S",
          "standardConceptCaption": "Standard",
          "invalidReasonCaption": "Valid",
          "conceptCode": "OMOP5017252",
          "domainId": "Drug",
          "vocabularyId": "RxNorm Extension",
          "conceptClassId": "Clinical Drug",
          "validStartDate": "2020-10-02",
          "validEndDate": "2099-12-31"
        },
        "isExcluded": false,
        "includeDescendants": false,
        "includeMapped": false
      },
      {
        "concept": {
          "conceptId": 35861089,
          "conceptName": "levofloxacin 400 MG Injectable Solution",
          "standardConcept": "S",
          "standardConceptCaption": "Standard",
          "invalidReasonCaption": "Valid",
          "conceptCode": "OMOP5017279",
          "domainId": "Drug",
          "vocabularyId": "RxNorm Extension",
          "conceptClassId": "Clinical Drug",
          "validStartDate": "2020-10-02",
          "validEndDate": "2099-12-31"
        },
        "isExcluded": false,
        "includeDescendants": false,
        "includeMapped": false
      },
      {
        "concept": {
          "conceptId": 35861099,
          "conceptName": "levofloxacin 300 MG Injectable Solution",
          "standardConcept": "S",
          "standardConceptCaption": "Standard",
          "invalidReasonCaption": "Valid",
          "conceptCode": "OMOP5017289",
          "domainId": "Drug",
          "vocabularyId": "RxNorm Extension",
          "conceptClassId": "Clinical Drug",
          "validStartDate": "2020-10-02",
          "validEndDate": "2099-12-31"
        },
        "isExcluded": false,
        "includeDescendants": false,
        "includeMapped": false
      },
      {
        "concept": {
          "conceptId": 35861133,
          "conceptName": "levofloxacin 200 MG Oral Tablet",
          "standardConcept": "S",
          "standardConceptCaption": "Standard",
          "invalidReasonCaption": "Valid",
          "conceptCode": "OMOP5017323",
          "domainId": "Drug",
          "vocabularyId": "RxNorm Extension",
          "conceptClassId": "Clinical Drug",
          "validStartDate": "2020-10-02",
          "validEndDate": "2099-12-31"
        },
        "isExcluded": false,
        "includeDescendants": false,
        "includeMapped": false
      },
      {
        "concept": {
          "conceptId": 35861137,
          "conceptName": "levofloxacin 200 MG Oral Capsule",
          "standardConcept": "S",
          "standardConceptCaption": "Standard",
          "invalidReasonCaption": "Valid",
          "conceptCode": "OMOP5017327",
          "domainId": "Drug",
          "vocabularyId": "RxNorm Extension",
          "conceptClassId": "Clinical Drug",
          "validStartDate": "2020-10-02",
          "validEndDate": "2099-12-31"
        },
        "isExcluded": false,
        "includeDescendants": false,
        "includeMapped": false
      },
      {
        "concept": {
          "conceptId": 35861138,
          "conceptName": "levofloxacin 200 MG Injectable Solution",
          "standardConcept": "S",
          "standardConceptCaption": "Standard",
          "invalidReasonCaption": "Valid",
          "conceptCode": "OMOP5017328",
          "domainId": "Drug",
          "vocabularyId": "RxNorm Extension",
          "conceptClassId": "Clinical Drug",
          "validStartDate": "2020-10-02",
          "validEndDate": "2099-12-31"
        },
        "isExcluded": false,
        "includeDescendants": false,
        "includeMapped": false
      },
      {
        "concept": {
          "conceptId": 35860768,
          "conceptName": "levofloxacin 15 MG Ophthalmic Solution",
          "standardConcept": "S",
          "standardConceptCaption": "Standard",
          "invalidReasonCaption": "Valid",
          "conceptCode": "OMOP5017373",
          "domainId": "Drug",
          "vocabularyId": "RxNorm Extension",
          "conceptClassId": "Clinical Drug",
          "validStartDate": "2020-10-02",
          "validEndDate": "2099-12-31"
        },
        "isExcluded": false,
        "includeDescendants": false,
        "includeMapped": false
      },
      {
        "concept": {
          "conceptId": 35860801,
          "conceptName": "levofloxacin 150 MG/ML Injectable Solution",
          "standardConcept": "S",
          "standardConceptCaption": "Standard",
          "invalidReasonCaption": "Valid",
          "conceptCode": "OMOP5017377",
          "domainId": "Drug",
          "vocabularyId": "RxNorm Extension",
          "conceptClassId": "Clinical Drug",
          "validStartDate": "2020-10-02",
          "validEndDate": "2099-12-31"
        },
        "isExcluded": false,
        "includeDescendants": false,
        "includeMapped": false
      },
      {
        "concept": {
          "conceptId": 35860805,
          "conceptName": "levofloxacin 80 MG/ML Injectable Solution",
          "standardConcept": "S",
          "standardConceptCaption": "Standard",
          "invalidReasonCaption": "Valid",
          "conceptCode": "OMOP5017381",
          "domainId": "Drug",
          "vocabularyId": "RxNorm Extension",
          "conceptClassId": "Clinical Drug",
          "validStartDate": "2020-10-02",
          "validEndDate": "2099-12-31"
        },
        "isExcluded": false,
        "includeDescendants": false,
        "includeMapped": false
      },
      {
        "concept": {
          "conceptId": 35860844,
          "conceptName": "levofloxacin 75 MG/ML Injectable Solution",
          "standardConcept": "S",
          "standardConceptCaption": "Standard",
          "invalidReasonCaption": "Valid",
          "conceptCode": "OMOP5017385",
          "domainId": "Drug",
          "vocabularyId": "RxNorm Extension",
          "conceptClassId": "Clinical Drug",
          "validStartDate": "2020-10-02",
          "validEndDate": "2099-12-31"
        },
        "isExcluded": false,
        "includeDescendants": false,
        "includeMapped": false
      },
      {
        "concept": {
          "conceptId": 35860846,
          "conceptName": "levofloxacin 60 MG/ML Injectable Solution",
          "standardConcept": "S",
          "standardConceptCaption": "Standard",
          "invalidReasonCaption": "Valid",
          "conceptCode": "OMOP5017387",
          "domainId": "Drug",
          "vocabularyId": "RxNorm Extension",
          "conceptClassId": "Clinical Drug",
          "validStartDate": "2020-10-02",
          "validEndDate": "2099-12-31"
        },
        "isExcluded": false,
        "includeDescendants": false,
        "includeMapped": false
      },
      {
        "concept": {
          "conceptId": 35860855,
          "conceptName": "levofloxacin 50 MG/ML Injectable Solution",
          "standardConcept": "S",
          "standardConceptCaption": "Standard",
          "invalidReasonCaption": "Valid",
          "conceptCode": "OMOP5017395",
          "domainId": "Drug",
          "vocabularyId": "RxNorm Extension",
          "conceptClassId": "Clinical Drug",
          "validStartDate": "2020-10-02",
          "validEndDate": "2099-12-31"
        },
        "isExcluded": false,
        "includeDescendants": false,
        "includeMapped": false
      },
      {
        "concept": {
          "conceptId": 35860865,
          "conceptName": "levofloxacin 40 MG/ML Injectable Solution",
          "standardConcept": "S",
          "standardConceptCaption": "Standard",
          "invalidReasonCaption": "Valid",
          "conceptCode": "OMOP5017405",
          "domainId": "Drug",
          "vocabularyId": "RxNorm Extension",
          "conceptClassId": "Clinical Drug",
          "validStartDate": "2020-10-02",
          "validEndDate": "2099-12-31"
        },
        "isExcluded": false,
        "includeDescendants": false,
        "includeMapped": false
      },
      {
        "concept": {
          "conceptId": 35860869,
          "conceptName": "levofloxacin 30 MG/ML Injectable Solution",
          "standardConcept": "S",
          "standardConceptCaption": "Standard",
          "invalidReasonCaption": "Valid",
          "conceptCode": "OMOP5017409",
          "domainId": "Drug",
          "vocabularyId": "RxNorm Extension",
          "conceptClassId": "Clinical Drug",
          "validStartDate": "2020-10-02",
          "validEndDate": "2099-12-31"
        },
        "isExcluded": false,
        "includeDescendants": false,
        "includeMapped": false
      },
      {
        "concept": {
          "conceptId": 35860873,
          "conceptName": "levofloxacin 20 MG/ML Injectable Solution",
          "standardConcept": "S",
          "standardConceptCaption": "Standard",
          "invalidReasonCaption": "Valid",
          "conceptCode": "OMOP5017413",
          "domainId": "Drug",
          "vocabularyId": "RxNorm Extension",
          "conceptClassId": "Clinical Drug",
          "validStartDate": "2020-10-02",
          "validEndDate": "2099-12-31"
        },
        "isExcluded": false,
        "includeDescendants": false,
        "includeMapped": false
      },
      {
        "concept": {
          "conceptId": 35860881,
          "conceptName": "levofloxacin 4 MG/ML Injectable Solution",
          "standardConcept": "S",
          "standardConceptCaption": "Standard",
          "invalidReasonCaption": "Valid",
          "conceptCode": "OMOP5017421",
          "domainId": "Drug",
          "vocabularyId": "RxNorm Extension",
          "conceptClassId": "Clinical Drug",
          "validStartDate": "2020-10-02",
          "validEndDate": "2099-12-31"
        },
        "isExcluded": false,
        "includeDescendants": false,
        "includeMapped": false
      },
      {
        "concept": {
          "conceptId": 35860887,
          "conceptName": "levofloxacin 3 MG/ML Ophthalmic Solution",
          "standardConcept": "S",
          "standardConceptCaption": "Standard",
          "invalidReasonCaption": "Valid",
          "conceptCode": "OMOP5017427",
          "domainId": "Drug",
          "vocabularyId": "RxNorm Extension",
          "conceptClassId": "Clinical Drug",
          "validStartDate": "2020-10-02",
          "validEndDate": "2099-12-31"
        },
        "isExcluded": false,
        "includeDescendants": false,
        "includeMapped": false
      },
      {
        "concept": {
          "conceptId": 35860889,
          "conceptName": "levofloxacin 3 MG/ML Injectable Solution",
          "standardConcept": "S",
          "standardConceptCaption": "Standard",
          "invalidReasonCaption": "Valid",
          "conceptCode": "OMOP5017429",
          "domainId": "Drug",
          "vocabularyId": "RxNorm Extension",
          "conceptClassId": "Clinical Drug",
          "validStartDate": "2020-10-02",
          "validEndDate": "2099-12-31"
        },
        "isExcluded": false,
        "includeDescendants": false,
        "includeMapped": false
      },
      {
        "concept": {
          "conceptId": 35860625,
          "conceptName": "levofloxacin 2.5 MG/ML Injectable Solution",
          "standardConcept": "S",
          "standardConceptCaption": "Standard",
          "invalidReasonCaption": "Valid",
          "conceptCode": "OMOP5017466",
          "domainId": "Drug",
          "vocabularyId": "RxNorm Extension",
          "conceptClassId": "Clinical Drug",
          "validStartDate": "2020-10-02",
          "validEndDate": "2099-12-31"
        },
        "isExcluded": false,
        "includeDescendants": false,
        "includeMapped": false
      },
      {
        "concept": {
          "conceptId": 35860631,
          "conceptName": "levofloxacin 2 MG/ML Injectable Solution",
          "standardConcept": "S",
          "standardConceptCaption": "Standard",
          "invalidReasonCaption": "Valid",
          "conceptCode": "OMOP5017472",
          "domainId": "Drug",
          "vocabularyId": "RxNorm Extension",
          "conceptClassId": "Clinical Drug",
          "validStartDate": "2020-10-02",
          "validEndDate": "2099-12-31"
        },
        "isExcluded": false,
        "includeDescendants": false,
        "includeMapped": false
      },
      {
        "concept": {
          "conceptId": 35860920,
          "conceptName": "levofloxacin 1.5 MG/ML Injectable Solution",
          "standardConcept": "S",
          "standardConceptCaption": "Standard",
          "invalidReasonCaption": "Valid",
          "conceptCode": "OMOP5017516",
          "domainId": "Drug",
          "vocabularyId": "RxNorm Extension",
          "conceptClassId": "Clinical Drug",
          "validStartDate": "2020-10-02",
          "validEndDate": "2099-12-31"
        },
        "isExcluded": false,
        "includeDescendants": false,
        "includeMapped": false
      },
      {
        "concept": {
          "conceptId": 35860924,
          "conceptName": "levofloxacin 1.2 MG/ML Injectable Solution",
          "standardConcept": "S",
          "standardConceptCaption": "Standard",
          "invalidReasonCaption": "Valid",
          "conceptCode": "OMOP5017520",
          "domainId": "Drug",
          "vocabularyId": "RxNorm Extension",
          "conceptClassId": "Clinical Drug",
          "validStartDate": "2020-10-02",
          "validEndDate": "2099-12-31"
        },
        "isExcluded": false,
        "includeDescendants": false,
        "includeMapped": false
      },
      {
        "concept": {
          "conceptId": 35860930,
          "conceptName": "levofloxacin 1 MG/ML Injectable Solution",
          "standardConcept": "S",
          "standardConceptCaption": "Standard",
          "invalidReasonCaption": "Valid",
          "conceptCode": "OMOP5017526",
          "domainId": "Drug",
          "vocabularyId": "RxNorm Extension",
          "conceptClassId": "Clinical Drug",
          "validStartDate": "2020-10-02",
          "validEndDate": "2099-12-31"
        },
        "isExcluded": false,
        "includeDescendants": false,
        "includeMapped": false
      },
      {
        "concept": {
          "conceptId": 35830693,
          "conceptName": "levofloxacin 0.1 MG/MG Oral Granules",
          "standardConcept": "S",
          "standardConceptCaption": "Standard",
          "invalidReasonCaption": "Valid",
          "conceptCode": "OMOP5037983",
          "domainId": "Drug",
          "vocabularyId": "RxNorm Extension",
          "conceptClassId": "Clinical Drug",
          "validStartDate": "2021-01-21",
          "validEndDate": "2099-12-31"
        },
        "isExcluded": false,
        "includeDescendants": false,
        "includeMapped": false
      },
      {
        "concept": {
          "conceptId": 41147891,
          "conceptName": "Levofloxacin 16.7 MG/ML Ophthalmic Solution",
          "standardConcept": "S",
          "standardConceptCaption": "Standard",
          "invalidReasonCaption": "Valid",
          "conceptCode": "OMOP2345853",
          "domainId": "Drug",
          "vocabularyId": "RxNorm Extension",
          "conceptClassId": "Clinical Drug",
          "validStartDate": "2017-08-24",
          "validEndDate": "2099-12-31"
        },
        "isExcluded": false,
        "includeDescendants": false,
        "includeMapped": false
      },
      {
        "concept": {
          "conceptId": 19107185,
          "conceptName": "levofloxacin 100 MG Oral Tablet",
          "standardConcept": "S",
          "standardConceptCaption": "Standard",
          "invalidReasonCaption": "Valid",
          "conceptCode": "430645",
          "domainId": "Drug",
          "vocabularyId": "RxNorm",
          "conceptClassId": "Clinical Drug",
          "validStartDate": "1970-01-01",
          "validEndDate": "2099-12-31"
        },
        "isExcluded": false,
        "includeDescendants": false,
        "includeMapped": false
      },
      {
        "concept": {
          "conceptId": 1742291,
          "conceptName": "levofloxacin 25 MG/ML Oral Solution",
          "standardConcept": "S",
          "standardConceptCaption": "Standard",
          "invalidReasonCaption": "Valid",
          "conceptCode": "477391",
          "domainId": "Drug",
          "vocabularyId": "RxNorm",
          "conceptClassId": "Clinical Drug",
          "validStartDate": "1970-01-01",
          "validEndDate": "2099-12-31"
        },
        "isExcluded": false,
        "includeDescendants": false,
        "includeMapped": false
      },
      {
        "concept": {
          "conceptId": 1742334,
          "conceptName": "levofloxacin 15 MG/ML Ophthalmic Solution",
          "standardConcept": "S",
          "standardConceptCaption": "Standard",
          "invalidReasonCaption": "Valid",
          "conceptCode": "545118",
          "domainId": "Drug",
          "vocabularyId": "RxNorm",
          "conceptClassId": "Clinical Drug",
          "validStartDate": "2005-09-11",
          "validEndDate": "2099-12-31"
        },
        "isExcluded": false,
        "includeDescendants": false,
        "includeMapped": false
      },
      {
        "concept": {
          "conceptId": 36880942,
          "conceptName": "Levofloxacin 5 MG/ML Prefilled Syringe",
          "standardConcept": "S",
          "standardConceptCaption": "Standard",
          "invalidReasonCaption": "Valid",
          "conceptCode": "OMOP1005844",
          "domainId": "Drug",
          "vocabularyId": "RxNorm Extension",
          "conceptClassId": "Clinical Drug",
          "validStartDate": "2017-08-24",
          "validEndDate": "2099-12-31"
        },
        "isExcluded": false,
        "includeDescendants": false,
        "includeMapped": false
      },
      {
        "concept": {
          "conceptId": 36788176,
          "conceptName": "Levofloxacin 5 MG/ML Intravenous Solution",
          "standardConcept": "S",
          "standardConceptCaption": "Standard",
          "invalidReasonCaption": "Valid",
          "conceptCode": "OMOP4776436",
          "domainId": "Drug",
          "vocabularyId": "RxNorm Extension",
          "conceptClassId": "Clinical Drug",
          "validStartDate": "2018-09-01",
          "validEndDate": "2099-12-31"
        },
        "isExcluded": false,
        "includeDescendants": false,
        "includeMapped": false
      },
      {
        "concept": {
          "conceptId": 35138534,
          "conceptName": "Levofloxacin 500 MG Disintegrating Oral Tablet",
          "standardConcept": "S",
          "standardConceptCaption": "Standard",
          "invalidReasonCaption": "Valid",
          "conceptCode": "OMOP4795694",
          "domainId": "Drug",
          "vocabularyId": "RxNorm Extension",
          "conceptClassId": "Clinical Drug",
          "validStartDate": "2019-03-11",
          "validEndDate": "2099-12-31"
        },
        "isExcluded": false,
        "includeDescendants": false,
        "includeMapped": false
      },
      {
        "concept": {
          "conceptId": 35151561,
          "conceptName": "Levofloxacin 25 MG/ML Injectable Solution",
          "standardConcept": "S",
          "standardConceptCaption": "Standard",
          "invalidReasonCaption": "Valid",
          "conceptCode": "OMOP4808608",
          "domainId": "Drug",
          "vocabularyId": "RxNorm Extension",
          "conceptClassId": "Clinical Drug",
          "validStartDate": "2019-03-11",
          "validEndDate": "2099-12-31"
        },
        "isExcluded": false,
        "includeDescendants": false,
        "includeMapped": false
      },
      {
        "concept": {
          "conceptId": 35151688,
          "conceptName": "Levofloxacin 100 MG/ML Oral Granules",
          "standardConcept": "S",
          "standardConceptCaption": "Standard",
          "invalidReasonCaption": "Valid",
          "conceptCode": "OMOP4808732",
          "domainId": "Drug",
          "vocabularyId": "RxNorm Extension",
          "conceptClassId": "Clinical Drug",
          "validStartDate": "2019-03-11",
          "validEndDate": "2099-12-31"
        },
        "isExcluded": false,
        "includeDescendants": false,
        "includeMapped": false
      },
      {
        "concept": {
          "conceptId": 35158540,
          "conceptName": "Levofloxacin 250 MG Disintegrating Oral Tablet",
          "standardConcept": "S",
          "standardConceptCaption": "Standard",
          "invalidReasonCaption": "Valid",
          "conceptCode": "OMOP4815534",
          "domainId": "Drug",
          "vocabularyId": "RxNorm Extension",
          "conceptClassId": "Clinical Drug",
          "validStartDate": "2019-03-11",
          "validEndDate": "2099-12-31"
        },
        "isExcluded": false,
        "includeDescendants": false,
        "includeMapped": false
      },
      {
        "concept": {
          "conceptId": 41053595,
          "conceptName": "Levofloxacin 10 MG/ML Ophthalmic Solution",
          "standardConcept": "S",
          "standardConceptCaption": "Standard",
          "invalidReasonCaption": "Valid",
          "conceptCode": "OMOP2251557",
          "domainId": "Drug",
          "vocabularyId": "RxNorm Extension",
          "conceptClassId": "Clinical Drug",
          "validStartDate": "2017-08-24",
          "validEndDate": "2099-12-31"
        },
        "isExcluded": false,
        "includeDescendants": false,
        "includeMapped": false
      },
      {
        "concept": {
          "conceptId": 43173611,
          "conceptName": "Levofloxacin 500 MG Delayed Release Oral Tablet",
          "standardConcept": "S",
          "standardConceptCaption": "Standard",
          "invalidReasonCaption": "Valid",
          "conceptCode": "OMOP497391",
          "domainId": "Drug",
          "vocabularyId": "RxNorm Extension",
          "conceptClassId": "Clinical Drug",
          "validStartDate": "2017-08-24",
          "validEndDate": "2099-12-31"
        },
        "isExcluded": false,
        "includeDescendants": false,
        "includeMapped": false
      }
    ]
  },
  "tags": [],
  "reviewStatus": "draft",
  "metadata": {
    "translations": {
      "en": {
        "name": "Levofloxacin",
        "category": "Drug",
        "subcategory": "Antimicrobials"
      },
      "fr": {
        "name": "Levofloxacin",
        "category": "Traitements",
        "subcategory": "Antimicrobiens"
      }
    },
    "createdByDetails": {
      "firstName": "Boris",
      "lastName": "Delange",
      "affiliation": "Univ Rennes, CHU Rennes, INSERM, LTSI-UMR 1099, Rennes, France",
      "profession": "Medical Informatics and Intensive Care Physician",
      "orcid": "0009-0002-6055-6935"
    },
    "reviews": [],
    "versions": [],
    "distributionStats": null
  }
}
